haystack_integrations/__init__.py
haystack_integrations/components/__init__.py
haystack_integrations/components/websearch/__init__.py
haystack_integrations/components/websearch/serpex.py
serpex_haystack-1.0.0.dist-info/METADATA
serpex_haystack-1.0.0.dist-info/WHEEL
serpex_haystack-1.0.0.dist-info/licenses/LICENSE
serpex_haystack-1.0.0.dist-info/RECORD
