Metadata-Version: 2.4
Name: serpex-haystack
Version: 1.0.0
Summary: Haystack integration for Serpex web search - supporting Google, Bing, DuckDuckGo, Brave, Yahoo, and Yandex
Project-URL: Homepage, https://serpex.dev
Project-URL: Documentation, https://docs.serpex.dev
Project-URL: Repository, https://github.com/divyeshradadiya/serpex-haystack
Project-URL: Issues, https://github.com/divyeshradadiya/serpex-haystack/issues
Author-email: Divyesh Radadiya <divyeshradadiya0@gmail.com>
License-Expression: Apache-2.0
License-File: LICENSE
Keywords: ai,bing-search,duckduckgo,google-search,haystack,llm,nlp,search-api,serpex,web-search
Classifier: Development Status :: 5 - Production/Stable
Classifier: Intended Audience :: Developers
Classifier: License :: OSI Approved :: Apache Software License
Classifier: Operating System :: OS Independent
Classifier: Programming Language :: Python :: 3
Classifier: Programming Language :: Python :: 3.8
Classifier: Programming Language :: Python :: 3.9
Classifier: Programming Language :: Python :: 3.10
Classifier: Programming Language :: Python :: 3.11
Classifier: Programming Language :: Python :: 3.12
Classifier: Topic :: Internet :: WWW/HTTP :: Indexing/Search
Classifier: Topic :: Scientific/Engineering :: Artificial Intelligence
Requires-Python: >=3.8
Requires-Dist: haystack-ai>=2.0.0
Requires-Dist: httpx>=0.24.0
Requires-Dist: tenacity>=8.0.0
Provides-Extra: dev
Requires-Dist: black>=23.0.0; extra == 'dev'
Requires-Dist: mypy>=1.0.0; extra == 'dev'
Requires-Dist: pre-commit>=3.0.0; extra == 'dev'
Requires-Dist: pytest-asyncio>=0.21.0; extra == 'dev'
Requires-Dist: pytest-cov>=4.0.0; extra == 'dev'
Requires-Dist: pytest>=7.0.0; extra == 'dev'
Requires-Dist: ruff>=0.1.0; extra == 'dev'
